MANIFEST.in
setup.py
src/icc/__init__.py
src/icc/test.py
src/icc.dme.fd.egg-info/PKG-INFO
src/icc.dme.fd.egg-info/SOURCES.txt
src/icc.dme.fd.egg-info/dependency_links.txt
src/icc.dme.fd.egg-info/namespace_packages.txt
src/icc.dme.fd.egg-info/requires.txt
src/icc.dme.fd.egg-info/top_level.txt
src/icc.dme.fd.egg-info/zip-safe
src/icc/dme/__init__.py
src/icc/dme/fd/Exploration.py
src/icc/dme/fd/Exploration2.py
src/icc/dme/fd/Forest.py
src/icc/dme/fd/ForestResources3.py
src/icc/dme/fd/Graphs.py
src/icc/dme/fd/START_VOL.py
src/icc/dme/fd/__init__.py
src/icc/dme/fd/dm.py
src/icc/dme/fd/gen_cryt.py
src/icc/dme/fd/mutils.py
src/icc/dme/fd/quant.py
src/icc/dme/fd/C/DModel.c