Metadata-Version: 1.0
Name: icc.dme.fd
Version: 0.0.5
Summary: Dynamic Modelling Environment
Home-page: UNKNOWN
Author: Evgeny Cherkashin
Author-email: eugeneai@irnok.net
License: GNU GPL
Keywords: forest resources dynamics analysis tool application
Platform: UNKNOWN
